vsengine/__init__.py
vsengine/_futures.py
vsengine/_helpers.py
vsengine/_hospice.py
vsengine/_nodes.py
vsengine/_version.py
vsengine/loops.py
vsengine/policy.py
vsengine/py.typed
vsengine/video.py
vsengine/vpy.py
vsengine/adapters/__init__.py
vsengine/adapters/asyncio.py
vsengine/adapters/trio.py
vsjetengine-1.0.0.dist-info/METADATA
vsjetengine-1.0.0.dist-info/WHEEL
vsjetengine-1.0.0.dist-info/licenses/COPYING
vsjetengine-1.0.0.dist-info/RECORD
