Metadata-Version: 2.4
Name: vsjetengine
Version: 1.0.0
Summary: An engine for vapoursynth previewers, renderers and script analyis tools.
Project-URL: Source Code, https://github.com/Jaded-Encoding-Thaumaturgy/vs-engine
Project-URL: Contact, https://discord.gg/XTpc6Fa9eB
Author-email: cid-chan <cid+git@cid-chan.moe>
Maintainer-email: Vardë <ichunjo.le.terrible@gmail.com>, Jaded Encoding Thaumaturgy <jaded.encoding.thaumaturgy@gmail.com>
License:                       EUROPEAN UNION PUBLIC LICENCE v. 1.2
License-File: COPYING
Classifier: Development Status :: 5 - Production/Stable
Classifier: License :: OSI Approved :: European Union Public Licence 1.2 (EUPL 1.2)
Classifier: Natural Language :: English
Classifier: Operating System :: OS Independent
Classifier: Programming Language :: Python :: 3
Classifier: Programming Language :: Python :: 3 :: Only
Classifier: Programming Language :: Python :: 3.12
Classifier: Programming Language :: Python :: 3.13
Classifier: Programming Language :: Python :: 3.14
Classifier: Topic :: Multimedia :: Graphics
Classifier: Typing :: Typed
Requires-Python: >=3.12
Requires-Dist: vapoursynth>=69
Provides-Extra: trio
Requires-Dist: trio; extra == 'trio'
